authlib/__init__.py
authlib/consts.py
authlib/deprecate.py
authlib/common/__init__.py
authlib/common/encoding.py
authlib/common/errors.py
authlib/common/security.py
authlib/common/urls.py
authlib/integrations/__init__.py
authlib/integrations/base_client/__init__.py
authlib/integrations/base_client/async_app.py
authlib/integrations/base_client/async_openid.py
authlib/integrations/base_client/errors.py
authlib/integrations/base_client/framework_integration.py
authlib/integrations/base_client/registry.py
authlib/integrations/base_client/sync_app.py
authlib/integrations/base_client/sync_openid.py
authlib/integrations/django_client/__init__.py
authlib/integrations/django_client/apps.py
authlib/integrations/django_client/integration.py
authlib/integrations/django_oauth1/__init__.py
authlib/integrations/django_oauth1/authorization_server.py
authlib/integrations/django_oauth1/nonce.py
authlib/integrations/django_oauth1/resource_protector.py
authlib/integrations/django_oauth2/__init__.py
authlib/integrations/django_oauth2/authorization_server.py
authlib/integrations/django_oauth2/endpoints.py
authlib/integrations/django_oauth2/requests.py
authlib/integrations/django_oauth2/resource_protector.py
authlib/integrations/django_oauth2/signals.py
authlib/integrations/flask_client/__init__.py
authlib/integrations/flask_client/apps.py
authlib/integrations/flask_client/integration.py
authlib/integrations/flask_oauth1/__init__.py
authlib/integrations/flask_oauth1/authorization_server.py
authlib/integrations/flask_oauth1/cache.py
authlib/integrations/flask_oauth1/resource_protector.py
authlib/integrations/flask_oauth2/__init__.py
authlib/integrations/flask_oauth2/authorization_server.py
authlib/integrations/flask_oauth2/errors.py
authlib/integrations/flask_oauth2/requests.py
authlib/integrations/flask_oauth2/resource_protector.py
authlib/integrations/flask_oauth2/signals.py
authlib/integrations/httpx_client/__init__.py
authlib/integrations/httpx_client/assertion_client.py
Authlib-1.2.1.dist-info/LICENSE
Authlib-1.2.1.dist-info/METADATA
Authlib-1.2.1.dist-info/WHEEL
Authlib-1.2.1.dist-info/top_level.txt
Authlib-1.2.1.dist-info/RECORD
